{
  "particles": {
    "number": {
      "value": 100
    },
    "color": {
      "value": "#aaa"
    },
    "shape": {
      "type": "circle"
    },
    "size": {
      "value": 2
    },
    "line_linked": {
      "enable": true,
      "distance": 150,
      "color": "#aaa",
      "opacity": 0.6,
      "width": 1
    },
    "move": {
      "enable": true,
      "speed": 4
    }
  },
  "interactivity": {
    "events": {
      "onhover": {
        "enable": true,
        "mode": "repulse"
      },
      "onclick": {
        "enable": true,
        "mode": "push"
      }
    },
    "modes": {
      "repulse": {
        "distance": 150,
        "duration": 0.4
      },
      "push": {
        "particles_nb": 1
      }
  }
  }
}
